build/lib/core/pgcore/__init__.py
build/lib/core/python/doxygen.py
build/lib/core/python/environment_for_pygimli_build.py
build/lib/core/python/generate_pygimli_code.py
build/lib/core/python/hand_made_wrappers.py
build/lib/core/python/patch_pygccxml.py
build/lib/core/python/apps/script_template.py
build/lib/doc/bib2html.py
build/lib/doc/conf.py
build/lib/doc/mplstyle.py
build/lib/doc/paper_carousel.py
build/lib/doc/sidebar_gallery.py
build/lib/doc/_sphinx-ext/srclinks.py
build/lib/doc/_templates/pybtex_plugins/pybtexPGstylePlugin.py
build/lib/doc/_templates/pybtex_plugins/setup.py
build/lib/doc/examples/1_meshing/plot_bert-logo.py
build/lib/doc/examples/1_meshing/plot_cad_tutorial.py
build/lib/doc/examples/1_meshing/plot_extrude_2D_to_3D.py
build/lib/doc/examples/1_meshing/plot_gmsh-example.py
build/lib/doc/examples/1_meshing/plot_hybrid-mesh-2d.py
build/lib/doc/examples/2_seismics/plot_01_refraction_manager.py
build/lib/doc/examples/2_seismics/plot_02_crosshole_tomography.py
build/lib/doc/examples/2_seismics/plot_03_rays_layered_and_gradient_models.py
build/lib/doc/examples/2_seismics/plot_04_koenigsee.py
build/lib/doc/examples/2_seismics/plot_05_refraction_3D.py
build/lib/doc/examples/3_ert/plot_01_ert_2d_mod_inv.py
build/lib/doc/examples/3_ert/plot_02_ert_field_data.py
build/lib/doc/examples/3_ert/plot_03_ert_2_layer_mod.py
build/lib/doc/examples/3_ert/plot_04_ert_2_5d_potential.py
build/lib/doc/examples/3_ert/plot_05_ert_4_point_sensitivities.py
build/lib/doc/examples/3_ert/plot_06_ert_crosshole2d.py
build/lib/doc/examples/3_ert/plot_06_ert_tree.py
build/lib/doc/examples/3_ert/plot_07_ert_3dsurface.py
build/lib/doc/examples/3_ert/plot_08_ert_crosshole3d.py
build/lib/doc/examples/3_ert/plot_09_ert_timelapse.py
build/lib/doc/examples/3_ert/plot_10_reciprocal_analysis.py
build/lib/doc/examples/3_ert/plot_modTank3d.py
build/lib/doc/examples/3_induced_polarization/plot_02_generating_sip_signatures.py
pygimli-1.5.5.dist-info/licenses/LICENSE.md
pygimli-1.5.5.dist-info/METADATA
pygimli-1.5.5.dist-info/WHEEL
pygimli-1.5.5.dist-info/top_level.txt
pygimli-1.5.5.dist-info/RECORD
