Metadata-Version: 2.4
Name: pygimli
Version: 1.5.5
Summary: Geophysical Inversion and Modelling Library
Author: Carsten Rücker, Thomas Günther, Florian Wagner
Author-email: mail@pygimli.org
License-Expression: Apache-2.0
Project-URL: Homepage, https://www.pygimli.org
Project-URL: Documentation, https://www.pygimli.org/documentation.html
Project-URL: Repository, https://github.com/gimli-org/gimli
Project-URL: Bug Tracker, https://github.com/gimli-org/gimli/issues
Project-URL: Changelog, https://github.com/gimli-org/gimli/releases
Keywords: Geophysical Inversion,Geophysical Modelling
Classifier: Development Status :: 5 - Production/Stable
Classifier: Programming Language :: Python
Classifier: Intended Audience :: Science/Research
Classifier: Programming Language :: Python :: 3 :: Only
Classifier: Topic :: Scientific/Engineering
Requires-Python: >=3.10
License-File: LICENSE.md
Requires-Dist: numpy>=2.1.3
Requires-Dist: setuptools>=75.8.2
Requires-Dist: scooby
Provides-Extra: build
Requires-Dist: pygccxml==2.5.0; extra == "build"
Requires-Dist: pyplusplus==1.8.5; extra == "build"
Requires-Dist: build; extra == "build"
Requires-Dist: twine; extra == "build"
Requires-Dist: wheel; extra == "build"
Requires-Dist: auditwheel; sys_platform == "linux" and extra == "build"
Requires-Dist: delvewheel; sys_platform == "win32" and extra == "build"
Requires-Dist: delocate; sys_platform == "darwin" and extra == "build"
Provides-Extra: opt
Requires-Dist: ipython; extra == "opt"
Requires-Dist: matplotlib>3.7; extra == "opt"
Requires-Dist: meshio; extra == "opt"
Requires-Dist: pyvista[all]; extra == "opt"
Requires-Dist: scipy<1.15,>=1.14; extra == "opt"
Requires-Dist: tetgen>=0.6.5; extra == "opt"
Requires-Dist: tqdm; extra == "opt"
Provides-Extra: test
Requires-Dist: pygimli[build,opt]; extra == "test"
Requires-Dist: tox; extra == "test"
Requires-Dist: ruff; extra == "test"
Requires-Dist: coverage[toml]; extra == "test"
Requires-Dist: pytest>=6.0; extra == "test"
Requires-Dist: pytest-cov; extra == "test"
Requires-Dist: pytest-html; extra == "test"
Requires-Dist: pylint; extra == "test"
Provides-Extra: doc
Requires-Dist: pygimli[test]; extra == "doc"
Requires-Dist: bibtexparser; extra == "doc"
Requires-Dist: jupytext; extra == "doc"
Requires-Dist: linkify-it-py; extra == "doc"
Requires-Dist: myst_nb; extra == "doc"
Requires-Dist: pydata-sphinx-theme; extra == "doc"
Requires-Dist: gmsh; extra == "doc"
Requires-Dist: sphinx>=7.2; extra == "doc"
Requires-Dist: sphinxcontrib-bibtex; extra == "doc"
Requires-Dist: sphinxcontrib-doxylink; extra == "doc"
Requires-Dist: sphinxcontrib-programoutput; extra == "doc"
Requires-Dist: sphinx-gallery; extra == "doc"
Requires-Dist: sphinx-design; extra == "doc"
Provides-Extra: dev
Requires-Dist: pygimli[build,doc,opt,test]; extra == "dev"
Provides-Extra: all
Requires-Dist: pygimli[dev]; extra == "all"
Dynamic: license-file
